streamcables/__init__.py
streamcables/arg.py
streamcables/icecast.py
streamcables/logger.py
streamcables/settings.py
streamcables/stdout.py
streamcables/streamcables.py
streamcables/twitter.py
streamcables-0.1.0.dist-info/LICENSE
streamcables-0.1.0.dist-info/WHEEL
streamcables-0.1.0.dist-info/METADATA
streamcables-0.1.0.dist-info/RECORD
